bmi260/BMI270.py
bmi260/config_file.py
bmi260/definitions.py
bmi260/registers.py
bmi260-0.4.5.dist-info/LICENSE
bmi260-0.4.5.dist-info/METADATA
bmi260-0.4.5.dist-info/WHEEL
bmi260-0.4.5.dist-info/top_level.txt
bmi260-0.4.5.dist-info/RECORD
