Metadata-Version: 2.1
Name: bmi260
Version: 0.4.5
Summary: BMI260/BMI270 I2C Python library (bare bones)
Author-email: Kevin Sommler <sommler@live.de>, Oleg Sayakhov <olegsajaxov@yandex.ru>
License: MIT
Project-URL: Homepage, https://github.com/architector1324/bmi260_python
Project-URL: Bug Tracker, https://github.com/architector1324/bmi260_python/issues
Keywords: BMI270,BMI260,I2C,IMU,sensor,driver,accelerometer,gyroscope,gyro,bosch,sensortech,smbus2,library
Classifier: Programming Language :: Python :: 3
Classifier: Intended Audience :: Developers
Classifier: License :: OSI Approved :: MIT License
Classifier: Topic :: Software Development :: Libraries
Classifier: Topic :: System :: Hardware
Requires-Python: >=3.7
License-File: LICENSE
Requires-Dist: smbus2 >=0.4.2
